Workbook

Sheet Read Me
A1: 📈 BTC EDGE TRACKER — multi-setup
A3: WHAT THIS IS
A4: A scoreboard that tells you — with numbers AND lessons — whether each setup makes money. Open just THIS file each trading day; everything is here.
A6: HOW TO USE IT
A7: 1. Trade ONLY Setup 1 to start ('My Setups' tab holds your definitions).
A8: 2. Log each trade's numbers in 'Trade Log', then add emotion + lesson in 'Journal'.
A9: 3. Check 'Dashboard' for each setup's Expectancy + Verdict. 'Reviews' = weekly/monthly.
A11: THE GOLDEN RULE
A12: Test on DEMO for 30+ trades per setup before risking real money. Trade ONE setup at a time until its Verdict says EDGE ✓. Then add the next.
A14: HOW TO READ THE VERDICT
A15: EDGE ✓ = positive expectancy over 30+ trades — a real edge, keep trading it.
A16: NO EDGE ✗ = it loses over time — fix or drop it, no matter how good the trades felt.

Sheet My Setups
A1: MY SETUPS — edit the cells to make them yours
A2: Start with Setup 1. Test ONE at a time on demo for 30+ trades. Only add the next setup after the current one's Verdict is EDGE ✓.
B3: SETUP 1 ★ START HERE | C3: SETUP 2 | D3: SETUP 3
A4: Setup name | B4: 4H Order Block Continuation | C4: Liquidity Sweep Reversal | D4: 4H Fair Value Gap Continuation
A5: Best for | B5: START HERE. Most objective. Beginner-friendly. | C5: Intermediate. Catches reversals at extremes. Needs patience. | D5: Trending markets. Fewer but very clean signals.
A6: Market bias | B6: WITH the Daily trend. | C6: Counter-move, only at obvious range highs/lows. | D6: WITH a strong Daily / 4H trend.
A7: Higher-TF filter | B7: Daily clearly trending (HH/HL or LH/LL). Skip if ranging. | C7: Price at an obvious liquidity pool: equal highs/lows or a clear prior swing. | D7: A strong impulsive 4H leg that left an imbalance (gap between wicks).
A8: Entry trigger | B8: Retrace into an unmitigated 4H OB -> 1H CHoCH in trend direction -> enter the 1H OB / FVG. | C8: Sweep the liquidity (wick beyond high/low) -> price reclaims -> 1H CHoCH back -> enter the OB / FVG from that CHoCH. | D8: Retrace into the 4H FVG (discount for longs / premium for shorts) -> 1H rejection or CHoCH -> enter inside the FVG.
A9: 3 confluences | B9: 1) Daily trend 2) 4H Order Block 3) 1H CHoCH | C9: 1) Liquidity swept 2) Reclaim/CHoCH 3) Entry FVG/OB | D9: 1) Trend 2) 4H FVG 3) 1H confirmation
A10: Stop-loss | B10: Beyond the far side of the 4H OB + buffer. | C10: Beyond the sweep wick extreme + buffer. | D10: Beyond the far edge of the FVG / the swing that made it.
A11: Take-profit | B11: Nearest opposing liquidity (swing low/high). Min 1:2. BE at TP1. | C11: Opposite liquidity or mid-range equilibrium. Min 1:2. | D11: Continuation to prior swing / next liquidity. Min 1:2.
A12: Invalidation | B12: 1H candle closes beyond the far side of the OB. | C12: Price closes beyond the sweep extreme (no reclaim). | D12: 4H candle closes fully through and past the FVG.
A13: Kill zone | B13: London 07-09 UTC / NY 13-15 UTC | C13: London 07-09 UTC / NY 13-15 UTC | D13: London 07-09 UTC / NY 13-15 UTC
A14: Min Risk:Reward | B14: 1:2 (prefer 1:3) | C14: 1:2 (prefer 1:3) | D14: 1:2 (prefer 1:3)
A15: Warning | B15: No Order Block = no trade. Never chase mid-range. | C15: Riskier — a sweep can keep running. Wait for the reclaim. | D15: Only in strong trends. In chop, FVGs fill and fail.

Sheet Trade Log
A1: LOG EVERY TRADE (demo first). Enter the WHITE cells — grey columns calculate themselves.
A2: You fill: Date, Setup (dropdown), Direction (dropdown), Entry, Stop, Exit, Followed rules? (dropdown), Notes. Auto: Risk/unit, R Multiple, Result. Row 4 = EXAMPLE (not counted). Real trades start row 5.
A3: # | B3: Date | C3: Setup | D3: Direction | E3: Entry | F3: Stop | G3: Exit | H3: Risk/unit | I3: R Multiple | J3: Result | K3: Followed rules? (Y/N) | L3: Notes
A4: EX | B4: 2026-07-20 | C4: Setup 1 | D4: SHORT | E4: 65500 | F4: 66000 | G4: 64500 | H4: =IF(OR($E4="",$F4=""),"",ABS($E4-$F4)) -> 500 | I4: =IF(OR($E4="",$F4="",$G4="",$H4=0),"",(($G4-$E4)*IF($D4="LONG",1,-1))/$H4) -> 2 | J4: =IF($I4="","",IF($I4>0,"WIN",IF($I4<0,"LOSS","BE"))) -> WIN | K4: Y | L4: EXAMPLE — overwrite from row 5. Not counted.
H5: =IF(OR($E5="",$F5=""),"",ABS($E5-$F5)) | I5: =IF(OR($E5="",$F5="",$G5="",$H5=0),"",(($G5-$E5)*IF($D5="LONG",1,-1))/$H5) | J5: =IF($I5="","",IF($I5>0,"WIN",IF($I5<0,"LOSS","BE")))
H6: =IF(OR($E6="",$F6=""),"",ABS($E6-$F6)) | I6: =IF(OR($E6="",$F6="",$G6="",$H6=0),"",(($G6-$E6)*IF($D6="LONG",1,-1))/$H6) | J6: =IF($I6="","",IF($I6>0,"WIN",IF($I6<0,"LOSS","BE")))
H7: =IF(OR($E7="",$F7=""),"",ABS($E7-$F7)) | I7: =IF(OR($E7="",$F7="",$G7="",$H7=0),"",(($G7-$E7)*IF($D7="LONG",1,-1))/$H7) | J7: =IF($I7="","",IF($I7>0,"WIN",IF($I7<0,"LOSS","BE")))
H8: =IF(OR($E8="",$F8=""),"",ABS($E8-$F8)) | I8: =IF(OR($E8="",$F8="",$G8="",$H8=0),"",(($G8-$E8)*IF($D8="LONG",1,-1))/$H8) | J8: =IF($I8="","",IF($I8>0,"WIN",IF($I8<0,"LOSS","BE")))
H9: =IF(OR($E9="",$F9=""),"",ABS($E9-$F9)) | I9: =IF(OR($E9="",$F9="",$G9="",$H9=0),"",(($G9-$E9)*IF($D9="LONG",1,-1))/$H9) | J9: =IF($I9="","",IF($I9>0,"WIN",IF($I9<0,"LOSS","BE")))
H10: =IF(OR($E10="",$F10=""),"",ABS($E10-$F10)) | I10: =IF(OR($E10="",$F10="",$G10="",$H10=0),"",(($G10-$E10)*IF($D10="LONG",1,-1))/$H10) | J10: =IF($I10="","",IF($I10>0,"WIN",IF($I10<0,"LOSS","BE")))
H11: =IF(OR($E11="",$F11=""),"",ABS($E11-$F11)) | I11: =IF(OR($E11="",$F11="",$G11="",$H11=0),"",(($G11-$E11)*IF($D11="LONG",1,-1))/$H11) | J11: =IF($I11="","",IF($I11>0,"WIN",IF($I11<0,"LOSS","BE")))
H12: =IF(OR($E12="",$F12=""),"",ABS($E12-$F12)) | I12: =IF(OR($E12="",$F12="",$G12="",$H12=0),"",(($G12-$E12)*IF($D12="LONG",1,-1))/$H12) | J12: =IF($I12="","",IF($I12>0,"WIN",IF($I12<0,"LOSS","BE")))
H13: =IF(OR($E13="",$F13=""),"",ABS($E13-$F13)) | I13: =IF(OR($E13="",$F13="",$G13="",$H13=0),"",(($G13-$E13)*IF($D13="LONG",1,-1))/$H13) | J13: =IF($I13="","",IF($I13>0,"WIN",IF($I13<0,"LOSS","BE")))
H14: =IF(OR($E14="",$F14=""),"",ABS($E14-$F14)) | I14: =IF(OR($E14="",$F14="",$G14="",$H14=0),"",(($G14-$E14)*IF($D14="LONG",1,-1))/$H14) | J14: =IF($I14="","",IF($I14>0,"WIN",IF($I14<0,"LOSS","BE")))
H15: =IF(OR($E15="",$F15=""),"",ABS($E15-$F15)) | I15: =IF(OR($E15="",$F15="",$G15="",$H15=0),"",(($G15-$E15)*IF($D15="LONG",1,-1))/$H15) | J15: =IF($I15="","",IF($I15>0,"WIN",IF($I15<0,"LOSS","BE")))
H16: =IF(OR($E16="",$F16=""),"",ABS($E16-$F16)) | I16: =IF(OR($E16="",$F16="",$G16="",$H16=0),"",(($G16-$E16)*IF($D16="LONG",1,-1))/$H16) | J16: =IF($I16="","",IF($I16>0,"WIN",IF($I16<0,"LOSS","BE")))
... H104: =IF(OR($E104="",$F104=""),"",ABS($E104-$F104)) | I104: =IF(OR($E104="",$F104="",$G104="",$H104=0),"",(($G104-$E104)*IF($D104="LONG",1,-1))/$H104) | J104: =IF($I104="","",IF($I104>0,"WIN",IF($I104<0,"LOSS","BE")))

Sheet Journal
A1: TRADE JOURNAL — the WHY behind each trade (numbers auto-fill from the Trade Log)
A2: #, Date, Setup, Result, R fill themselves from the Trade Log. You add: Emotion before/after, Mistake, Lesson. The 'Mistake' and 'Lesson' fields matter most — that is where you beat FOMO and emotion.
A3: # | B3: Date | C3: Setup | D3: Result | E3: R | F3: Emotion BEFORE | G3: Emotion AFTER | H3: Followed plan? | I3: Mistake / rule broken | J3: Lesson learned
A4: =IF('Trade Log'!A4="","",'Trade Log'!A4) -> EX | B4: =IF('Trade Log'!B4="","",'Trade Log'!B4) -> 2026-07-20 | C4: =IF('Trade Log'!C4="","",'Trade Log'!C4) -> Setup 1 | D4: =IF('Trade Log'!J4="","",'Trade Log'!J4) -> WIN | E4: =IF('Trade Log'!I4="","",'Trade Log'!I4) -> 2 | F4: Calm, waited for setup | G4: Confident, followed plan | H4: =IF('Trade Log'!K4="","",'Trade Log'!K4) -> Y | I4: None | J4: EXAMPLE — waiting paid off.
A5: =IF('Trade Log'!A5="","",'Trade Log'!A5) | B5: =IF('Trade Log'!B5="","",'Trade Log'!B5) | C5: =IF('Trade Log'!C5="","",'Trade Log'!C5) | D5: =IF('Trade Log'!J5="","",'Trade Log'!J5) | E5: =IF('Trade Log'!I5="","",'Trade Log'!I5) | H5: =IF('Trade Log'!K5="","",'Trade Log'!K5)
A6: =IF('Trade Log'!A6="","",'Trade Log'!A6) | B6: =IF('Trade Log'!B6="","",'Trade Log'!B6) | C6: =IF('Trade Log'!C6="","",'Trade Log'!C6) | D6: =IF('Trade Log'!J6="","",'Trade Log'!J6) | E6: =IF('Trade Log'!I6="","",'Trade Log'!I6) | H6: =IF('Trade Log'!K6="","",'Trade Log'!K6)
A7: =IF('Trade Log'!A7="","",'Trade Log'!A7) | B7: =IF('Trade Log'!B7="","",'Trade Log'!B7) | C7: =IF('Trade Log'!C7="","",'Trade Log'!C7) | D7: =IF('Trade Log'!J7="","",'Trade Log'!J7) | E7: =IF('Trade Log'!I7="","",'Trade Log'!I7) | H7: =IF('Trade Log'!K7="","",'Trade Log'!K7)
A8: =IF('Trade Log'!A8="","",'Trade Log'!A8) | B8: =IF('Trade Log'!B8="","",'Trade Log'!B8) | C8: =IF('Trade Log'!C8="","",'Trade Log'!C8) | D8: =IF('Trade Log'!J8="","",'Trade Log'!J8) | E8: =IF('Trade Log'!I8="","",'Trade Log'!I8) | H8: =IF('Trade Log'!K8="","",'Trade Log'!K8)
A9: =IF('Trade Log'!A9="","",'Trade Log'!A9) | B9: =IF('Trade Log'!B9="","",'Trade Log'!B9) | C9: =IF('Trade Log'!C9="","",'Trade Log'!C9) | D9: =IF('Trade Log'!J9="","",'Trade Log'!J9) | E9: =IF('Trade Log'!I9="","",'Trade Log'!I9) | H9: =IF('Trade Log'!K9="","",'Trade Log'!K9)
A10: =IF('Trade Log'!A10="","",'Trade Log'!A10) | B10: =IF('Trade Log'!B10="","",'Trade Log'!B10) | C10: =IF('Trade Log'!C10="","",'Trade Log'!C10) | D10: =IF('Trade Log'!J10="","",'Trade Log'!J10) | E10: =IF('Trade Log'!I10="","",'Trade Log'!I10) | H10: =IF('Trade Log'!K10="","",'Trade Log'!K10)
A11: =IF('Trade Log'!A11="","",'Trade Log'!A11) | B11: =IF('Trade Log'!B11="","",'Trade Log'!B11) | C11: =IF('Trade Log'!C11="","",'Trade Log'!C11) | D11: =IF('Trade Log'!J11="","",'Trade Log'!J11) | E11: =IF('Trade Log'!I11="","",'Trade Log'!I11) | H11: =IF('Trade Log'!K11="","",'Trade Log'!K11)
A12: =IF('Trade Log'!A12="","",'Trade Log'!A12) | B12: =IF('Trade Log'!B12="","",'Trade Log'!B12) | C12: =IF('Trade Log'!C12="","",'Trade Log'!C12) | D12: =IF('Trade Log'!J12="","",'Trade Log'!J12) | E12: =IF('Trade Log'!I12="","",'Trade Log'!I12) | H12: =IF('Trade Log'!K12="","",'Trade Log'!K12)
A13: =IF('Trade Log'!A13="","",'Trade Log'!A13) | B13: =IF('Trade Log'!B13="","",'Trade Log'!B13) | C13: =IF('Trade Log'!C13="","",'Trade Log'!C13) | D13: =IF('Trade Log'!J13="","",'Trade Log'!J13) | E13: =IF('Trade Log'!I13="","",'Trade Log'!I13) | H13: =IF('Trade Log'!K13="","",'Trade Log'!K13)
A14: =IF('Trade Log'!A14="","",'Trade Log'!A14) | B14: =IF('Trade Log'!B14="","",'Trade Log'!B14) | C14: =IF('Trade Log'!C14="","",'Trade Log'!C14) | D14: =IF('Trade Log'!J14="","",'Trade Log'!J14) | E14: =IF('Trade Log'!I14="","",'Trade Log'!I14) | H14: =IF('Trade Log'!K14="","",'Trade Log'!K14)
A15: =IF('Trade Log'!A15="","",'Trade Log'!A15) | B15: =IF('Trade Log'!B15="","",'Trade Log'!B15) | C15: =IF('Trade Log'!C15="","",'Trade Log'!C15) | D15: =IF('Trade Log'!J15="","",'Trade Log'!J15) | E15: =IF('Trade Log'!I15="","",'Trade Log'!I15) | H15: =IF('Trade Log'!K15="","",'Trade Log'!K15)
A16: =IF('Trade Log'!A16="","",'Trade Log'!A16) | B16: =IF('Trade Log'!B16="","",'Trade Log'!B16) | C16: =IF('Trade Log'!C16="","",'Trade Log'!C16) | D16: =IF('Trade Log'!J16="","",'Trade Log'!J16) | E16: =IF('Trade Log'!I16="","",'Trade Log'!I16) | H16: =IF('Trade Log'!K16="","",'Trade Log'!K16)
... A104: =IF('Trade Log'!A104="","",'Trade Log'!A104) | B104: =IF('Trade Log'!B104="","",'Trade Log'!B104) | C104: =IF('Trade Log'!C104="","",'Trade Log'!C104) | D104: =IF('Trade Log'!J104="","",'Trade Log'!J104) | E104: =IF('Trade Log'!I104="","",'Trade Log'!I104) | H104: =IF('Trade Log'!K104="","",'Trade Log'!K104)

Sheet Dashboard
A1: PER-SETUP SCORECARD — does each setup have an edge?
A2: Trust a verdict only after 30+ trades. Expectancy = average R won or lost per trade.
A4: Metric | B4: Setup 1 | C4: Setup 2 | D4: Setup 3 | E4: ALL COMBINED
A5: Trades logged | B5: =COUNTIFS('Trade Log'!$C$5:$C$104,"Setup 1",'Trade Log'!$J$5:$J$104,"WIN")+COUNTIFS('Trade Log'!$C$5:$C$104,"Setup 1",'Trade Log'!$J$5:$J$104,"LOSS")+COUNTIFS('Trade Log'!$C$5:$C$104,"Setup 1",'Trade Log'!$J$5:$J$104,"BE") -> 0 | C5: =COUNTIFS('Trade Log'!$C$5:$C$104,"Setup 2",'Trade Log'!$J$5:$J$104,"WIN")+COUNTIFS('Trade Log'!$C$5:$C$104,"Setup 2",'Trade Log'!$J$5:$J$104,"LOSS")+COUNTIFS('Trade Log'!$C$5:$C$104,"Setup 2",'Trade Log'!$J$5:$J$104,"BE") -> 0 | D5: =COUNTIFS('Trade Log'!$C$5:$C$104,"Setup 3",'Trade Log'!$J$5:$J$104,"WIN")+COUNTIFS('Trade Log'!$C$5:$C$104,"Setup 3",'Trade Log'!$J$5:$J$104,"LOSS")+COUNTIFS('Trade Log'!$C$5:$C$104,"Setup 3",'Trade Log'!$J$5:$J$104,"BE") -> 0 | E5: =COUNTIF('Trade Log'!$J$5:$J$104,"WIN")+COUNTIF('Trade Log'!$J$5:$J$104,"LOSS")+COUNTIF('Trade Log'!$J$5:$J$104,"BE") -> 0
A6: Wins | B6: =COUNTIFS('Trade Log'!$C$5:$C$104,"Setup 1",'Trade Log'!$J$5:$J$104,"WIN") -> 0 | C6: =COUNTIFS('Trade Log'!$C$5:$C$104,"Setup 2",'Trade Log'!$J$5:$J$104,"WIN") -> 0 | D6: =COUNTIFS('Trade Log'!$C$5:$C$104,"Setup 3",'Trade Log'!$J$5:$J$104,"WIN") -> 0 | E6: =COUNTIF('Trade Log'!$J$5:$J$104,"WIN") -> 0
A7: Losses | B7: =COUNTIFS('Trade Log'!$C$5:$C$104,"Setup 1",'Trade Log'!$J$5:$J$104,"LOSS") -> 0 | C7: =COUNTIFS('Trade Log'!$C$5:$C$104,"Setup 2",'Trade Log'!$J$5:$J$104,"LOSS") -> 0 | D7: =COUNTIFS('Trade Log'!$C$5:$C$104,"Setup 3",'Trade Log'!$J$5:$J$104,"LOSS") -> 0 | E7: =COUNTIF('Trade Log'!$J$5:$J$104,"LOSS") -> 0
A8: Breakeven | B8: =COUNTIFS('Trade Log'!$C$5:$C$104,"Setup 1",'Trade Log'!$J$5:$J$104,"BE") -> 0 | C8: =COUNTIFS('Trade Log'!$C$5:$C$104,"Setup 2",'Trade Log'!$J$5:$J$104,"BE") -> 0 | D8: =COUNTIFS('Trade Log'!$C$5:$C$104,"Setup 3",'Trade Log'!$J$5:$J$104,"BE") -> 0 | E8: =COUNTIF('Trade Log'!$J$5:$J$104,"BE") -> 0
A9: Win rate | B9: =IFERROR(COUNTIFS('Trade Log'!$C$5:$C$104,"Setup 1",'Trade Log'!$J$5:$J$104,"WIN")/(COUNTIFS('Trade Log'!$C$5:$C$104,"Setup 1",'Trade Log'!$J$5:$J$104,"WIN")+COUNTIFS('Trade Log'!$C$5:$C$104,"Setup 1",'Trade Log'!$J$5:$J$104,"LOSS")),"") | C9: =IFERROR(COUNTIFS('Trade Log'!$C$5:$C$104,"Setup 2",'Trade Log'!$J$5:$J$104,"WIN")/(COUNTIFS('Trade Log'!$C$5:$C$104,"Setup 2",'Trade Log'!$J$5:$J$104,"WIN")+COUNTIFS('Trade Log'!$C$5:$C$104,"Setup 2",'Trade Log'!$J$5:$J$104,"LOSS")),"") | D9: =IFERROR(COUNTIFS('Trade Log'!$C$5:$C$104,"Setup 3",'Trade Log'!$J$5:$J$104,"WIN")/(COUNTIFS('Trade Log'!$C$5:$C$104,"Setup 3",'Trade Log'!$J$5:$J$104,"WIN")+COUNTIFS('Trade Log'!$C$5:$C$104,"Setup 3",'Trade Log'!$J$5:$J$104,"LOSS")),"") | E9: =IFERROR(COUNTIF('Trade Log'!$J$5:$J$104,"WIN")/(COUNTIF('Trade Log'!$J$5:$J$104,"WIN")+COUNTIF('Trade Log'!$J$5:$J$104,"LOSS")),"")
A10: Avg WIN (R) | B10: =IFERROR(AVERAGEIFS('Trade Log'!$I$5:$I$104,'Trade Log'!$C$5:$C$104,"Setup 1",'Trade Log'!$I$5:$I$104,">0"),"") | C10: =IFERROR(AVERAGEIFS('Trade Log'!$I$5:$I$104,'Trade Log'!$C$5:$C$104,"Setup 2",'Trade Log'!$I$5:$I$104,">0"),"") | D10: =IFERROR(AVERAGEIFS('Trade Log'!$I$5:$I$104,'Trade Log'!$C$5:$C$104,"Setup 3",'Trade Log'!$I$5:$I$104,">0"),"") | E10: =IFERROR(AVERAGEIF('Trade Log'!$I$5:$I$104,">0"),"")
A11: Avg LOSS (R) | B11: =IFERROR(AVERAGEIFS('Trade Log'!$I$5:$I$104,'Trade Log'!$C$5:$C$104,"Setup 1",'Trade Log'!$I$5:$I$104,"<0"),"") | C11: =IFERROR(AVERAGEIFS('Trade Log'!$I$5:$I$104,'Trade Log'!$C$5:$C$104,"Setup 2",'Trade Log'!$I$5:$I$104,"<0"),"") | D11: =IFERROR(AVERAGEIFS('Trade Log'!$I$5:$I$104,'Trade Log'!$C$5:$C$104,"Setup 3",'Trade Log'!$I$5:$I$104,"<0"),"") | E11: =IFERROR(AVERAGEIF('Trade Log'!$I$5:$I$104,"<0"),"")
A12: Total R banked | B12: =SUMIFS('Trade Log'!$I$5:$I$104,'Trade Log'!$C$5:$C$104,"Setup 1") -> 0 | C12: =SUMIFS('Trade Log'!$I$5:$I$104,'Trade Log'!$C$5:$C$104,"Setup 2") -> 0 | D12: =SUMIFS('Trade Log'!$I$5:$I$104,'Trade Log'!$C$5:$C$104,"Setup 3") -> 0 | E12: =SUM('Trade Log'!$I$5:$I$104) -> 0
A14: EXPECTANCY (R / trade) | B14: =IFERROR(B12/B5,"") | C14: =IFERROR(C12/C5,"") | D14: =IFERROR(D12/D5,"") | E14: =IFERROR(E12/E5,"")
A15: VERDICT | B15: =IF(B5=0,"— no data —",IF(B5<30,"Need "&(30-B5)&" more",IF(B14>0,"EDGE ✓","NO EDGE ✗"))) -> — no data — | C15: =IF(C5=0,"— no data —",IF(C5<30,"Need "&(30-C5)&" more",IF(C14>0,"EDGE ✓","NO EDGE ✗"))) -> — no data — | D15: =IF(D5=0,"— no data —",IF(D5<30,"Need "&(30-D5)&" more",IF(D14>0,"EDGE ✓","NO EDGE ✗"))) -> — no data — | E15: =IF(E5=0,"— no data —",IF(E5<30,"Need "&(30-E5)&" more",IF(E14>0,"EDGE ✓","NO EDGE ✗"))) -> — no data —
A17: Rule adherence | B17: =IFERROR(COUNTIFS('Trade Log'!$C$5:$C$104,"Setup 1",'Trade Log'!$K$5:$K$104,"Y")/B5,"") | C17: =IFERROR(COUNTIFS('Trade Log'!$C$5:$C$104,"Setup 2",'Trade Log'!$K$5:$K$104,"Y")/C5,"") | D17: =IFERROR(COUNTIFS('Trade Log'!$C$5:$C$104,"Setup 3",'Trade Log'!$K$5:$K$104,"Y")/D5,"") | E17: =IFERROR(COUNTIF('Trade Log'!$K$5:$K$104,"Y")/E5,"")
A19: Read it: a positive Expectancy over 30+ trades is a real edge — keep trading that setup. Negative = stop and fix it. Rule adherence should be near 100%. Test on demo before real money.

Sheet Reviews
A1: WEEKLY & MONTHLY REVIEW — copy a block each period and fill the yellow cells
A3: 📅 WEEKLY REVIEW
A4: Week of
A5: Total trades
A6: Wins / Losses
A7: Win rate %
A8: Total R this week
A9: Capital (end)
A10: Best trade (why it worked)
A11: Worst trade (which rule slipped)
A12: Times I broke a rule | B12: target: fewer than last week
A13: One fix for next week
A15: 🏆 MONTHLY REVIEW
A16: Month
A17: Start / End capital
A18: Net return %
A19: Total trades
A20: Win rate %
A21: Avg win R / Avg loss R
A22: Best setup (from Dashboard)
A23: Discipline score (1-10) | B23: how well did I follow my rules?
A24: Biggest lesson
A25: Next month goal
A27: Track discipline, not just profit. On a small account, staying in the game IS winning.
